gm_libs/__init__.py
gm_libs/stock_shop.py
gm_libs-0.0.21.dist-info/METADATA
gm_libs-0.0.21.dist-info/WHEEL
gm_libs-0.0.21.dist-info/licenses/LICENSE
gm_libs-0.0.21.dist-info/RECORD
