Metadata-Version: 2.3
Name: gm_libs
Version: 0.0.21
Summary: A juejin quant lib to myself package
Project-URL: Homepage, https://github.com/Sun-FreePort/gm_libs
Project-URL: Issues, https://github.com/Sun-FreePort/gm_libs/issues
Project-URL: Website, https://www.uiosun.com
Author-email: UioSun <uiosun@outlook.com>
License-File: LICENSE
Classifier: License :: OSI Approved :: MIT License
Classifier: Operating System :: OS Independent
Classifier: Programming Language :: Python :: 3
Requires-Python: >=3.10
